jupyterhub_mlflow_auth.py
jupyterhub_mlflow_auth-1.0.1.dist-info/entry_points.txt
jupyterhub_mlflow_auth-1.0.1.dist-info/LICENSE
jupyterhub_mlflow_auth-1.0.1.dist-info/WHEEL
jupyterhub_mlflow_auth-1.0.1.dist-info/METADATA
jupyterhub_mlflow_auth-1.0.1.dist-info/RECORD
